bobaserver/__init__.py
bobaserver/common.py
bobaserver/monitor.py
bobaserver/routes.py
bobaserver/run_server.py
bobaserver/util.py
bobaserver/bobastats/__init__.py
bobaserver/bobastats/bootstrap.py
bobaserver/bobastats/sampling.py
bobaserver/bobastats/sensitivity.py
bobaserver/dist/blues-thick.png
bobaserver/dist/blues.png
bobaserver/dist/bundle.js
bobaserver/dist/bundle.js.map
bobaserver/dist/favicon.ico
bobaserver/dist/idl-logo.png
bobaserver/dist/index.html
bobaserver/dist/null.png
bobaserver/dist/simple.png
bobaserver/dist/stacking.png
bobaserver/dist/style.css
boba_visualizer-1.1.1.dist-info/LICENSE
boba_visualizer-1.1.1.dist-info/METADATA
boba_visualizer-1.1.1.dist-info/WHEEL
boba_visualizer-1.1.1.dist-info/entry_points.txt
boba_visualizer-1.1.1.dist-info/top_level.txt
boba_visualizer-1.1.1.dist-info/RECORD
