Metadata-Version: 2.1
Name: boba-visualizer
Version: 1.1.1
Summary: Visualize multiverse outcomes
Home-page: https://github.com/yyyliu/boba-visualizer
Author: Yang Liu
Author-email: yliu0@uw.edu
License: BSD license
Keywords: multiverse analysis
Platform: UNKNOWN
Classifier: Development Status :: 3 - Alpha
Classifier: Intended Audience :: Science/Research
Classifier: License :: OSI Approved :: BSD License
Classifier: Natural Language :: English
Classifier: Programming Language :: Python :: 3
Classifier: Programming Language :: Python :: 3.6
Classifier: Programming Language :: Python :: 3.7
Requires-Dist: flask (>=1.1.1)
Requires-Dist: Click (>=7.0)
Requires-Dist: pandas (>=1.0.1)
Requires-Dist: scipy (>=1.4.1)
Requires-Dist: boba (>=1.1.1)
Requires-Dist: flask-socketio (>=5.0.0)
Requires-Dist: apscheduler (>=3.7.0)
Requires-Dist: scikit-learn (>=0.24.1)
